mobilenet_v3/LR_ASPP.py
mobilenet_v3/__init__.py
mobilenet_v3/mobilenet_base.py
mobilenet_v3/mobilenet_v3_large.py
mobilenet_v3/mobilenet_v3_small.py
mobilenet_v3-0.1.4.data/scripts/LR_ASPP.py
mobilenet_v3-0.1.4.data/scripts/__init__.py
mobilenet_v3-0.1.4.data/scripts/bilinear_upsampling.py
mobilenet_v3-0.1.4.data/scripts/mobilenet_base.py
mobilenet_v3-0.1.4.data/scripts/mobilenet_v3_large.py
mobilenet_v3-0.1.4.data/scripts/mobilenet_v3_small.py
mobilenet_v3-0.1.4.dist-info/METADATA
mobilenet_v3-0.1.4.dist-info/RECORD
mobilenet_v3-0.1.4.dist-info/WHEEL
mobilenet_v3-0.1.4.dist-info/top_level.txt
mobilenetv3/LR_ASPP.py
mobilenetv3/__init__.py
mobilenetv3/mobilenet_base.py
mobilenetv3/mobilenet_v3_large.py
mobilenetv3/mobilenet_v3_small.py
