Metadata-Version: 2.1
Name: mobilenet-v3
Version: 0.1.4
Summary: A Keras implementation of MobileNetV3.
Home-page: https://github.com/xiaochus/MobileNetV3
Author: xiaochus
License: MIT
Platform: UNKNOWN
Classifier: Programming Language :: Python :: 3
Classifier: License :: OSI Approved :: MIT License
Classifier: Operating System :: OS Independent
